APiHole/APiHole.py
APiHole/__init__.py
APiHole/example.py
APiHole-0.0.1.dist-info/LICENSE
APiHole-0.0.1.dist-info/METADATA
APiHole-0.0.1.dist-info/WHEEL
APiHole-0.0.1.dist-info/top_level.txt
APiHole-0.0.1.dist-info/RECORD
