Metadata-Version: 2.1
Name: APiHole
Version: 0.0.1
Summary: API module for Pi Hole
Home-page: https://github.com/sdebby/APiHole
Author: Shmulik Debby
Author-email: shmulik.debby@gmail.com
License: MIT
Keywords: PiHole,pi.hole,API
Classifier: Development Status :: 1 - Planning
Classifier: Intended Audience :: Developers
Classifier: Programming Language :: Python :: 3
Classifier: Operating System :: Unix
Classifier: Operating System :: MacOS :: MacOS X
Classifier: Operating System :: Microsoft :: Windows
Classifier: License :: OSI Approved :: MIT License
License-File: LICENSE
Requires-Dist: requests
